empugn/__init__.py
empugn/__main__.py
empugn/input.py
empugn-0.1.0.dist-info/METADATA
empugn-0.1.0.dist-info/RECORD
empugn-0.1.0.dist-info/WHEEL
empugn-0.1.0.dist-info/entry_points.txt
empugn-0.1.0.dist-info/top_level.txt
empugn-0.1.0.dist-info/zip-safe
