Metadata-Version: 2.1
Name: empugn
Version: 0.1.0
Summary: Generate HTML or XML from YAML or JSON
Home-page: http://github.com/japsu/empugn
Author: Santtu Pajukanta
Author-email: santtu@pajukanta.fi
License: MIT
Platform: UNKNOWN
Provides-Extra: emrichen
Provides-Extra: yaml
Requires-Dist: yattag (~=1.10.1)
Provides-Extra: emrichen
Requires-Dist: emrichen; extra == 'emrichen'
Provides-Extra: yaml
Requires-Dist: PyYAML; extra == 'yaml'
